{
  "Điều 1": "Điều 1. Ban hành Quy chế",
  "Điều 2": "Điều 2. Trách nhiệm thi hành",
  "Điều 3": "Điều 3. Hiệu lực thi hành",
  "Khoản 1": "1. Nghị quyết này có hiệu lực thi hành từ ngày 01 tháng 10 năm 2025.",
  "Khoản 2": "2. Nghị quyết số 1213/2016/UBTVQH13 ngày 13 tháng 6 năm 2016 của Ủy ban Thường vụ Quốc hội ban hành Quy chế tổ chức và hoạt động của Đoàn Hội thẩm hết hiệu lực từ ngày Nghị quyết này có hiệu lực thi hành.",
  "Khoản 3": "3. Hội thẩm nhân dân nhiệm kỳ 2021 - 2026 đang thực hiện nhiệm vụ xét xử tại Tòa án nhân dân tỉnh, thành phố, Tòa án nhân dân khu vực theo quy định tại khoản 7 Điều 3 của Nghị quyết số 225/2025/QH15 ngày 27 tháng 6 năm 2025 của Quốc hội tham gia sinh hoạt tại Đoàn Hội thẩm nhân dân tỉnh, thành phố, Đoàn Hội thẩm nhân dân khu vực nơi thực hiện nhiệm vụ xét xử cho đến hết nhiệm kỳ. Tổ chức và hoạt động của Đoàn Hội thẩm nhân dân được thực hiện theo Quy chế ban hành kèm theo Nghị quyết này./."
}