{
  "id": "172438",
  "doc_number": "01/2018/UBTVQH14",
  "title": "Pháp lệnh số 01/2018/UBTVQH14 sửa đổi, bổ sung một số điều có liên quan đến quy hoạch của Pháp lệnh Công nghiệp quốc phòng số 02/2008/PL-UBTVQH12, Pháp lệnh Quản lý thị trường số 11/2016/UBTVQH13, Pháp lệnh Thư viện số 31/2000/PL-UBTVQH10, Pháp lệnh Ưu đãi người có công với cách mạng số 26/2005/PL-UBTVQH11 đã được sửa đổi, bổ sung một số điều theo Pháp lệnh số 04/2012/UBTVQH13",
  "doc_type": "Pháp lệnh",
  "agency": "Uỷ ban Thường vụ Quốc hội",
  "signer": "Nguyễn Thị Kim Ngân",
  "signer_title": "Chủ tịch",
  "issue_date": "2018-12-22",
  "effective_date": "2019-01-01",
  "expire_date": "--",
  "status": "Còn hiệu lực",
  "industry": "Quốc phòng",
  "field": "Công nghiệp quốc phòng",
  "relations": {
    "Căn cứ ban hành": [
      {
        "title": "Nghị quyết số 74/2018/QH14 Kỳ họp thứ 6, Quốc hội khóa XIV",
        "url": "https://vbpl.vn/van-ban/chi-tiet/doc--132353"
      },
      {
        "title": "Hiến pháp năm 2013",
        "url": "https://vbpl.vn/van-ban/chi-tiet/doc--32801"
      }
    ],
    "Văn bản được sửa đổi bổ sung": [
      {
        "title": "Pháp lệnh số 04/2012/UBTVQH13 Sửa đổi, bổ sung một số điều của Pháp lệnh ưu đãi người có công với cách mạng",
        "url": "https://vbpl.vn/van-ban/chi-tiet/doc--27708"
      },
      {
        "title": "Pháp lệnh số 26/2005/PL-UBTVQH11 Ưu đãi người có công với cách mạng",
        "url": "https://vbpl.vn/van-ban/chi-tiet/doc--17750"
      },
      {
        "title": "Pháp lệnh số 11/2016/UBTVQH13 Quản lý thị trường",
        "url": "https://vbpl.vn/van-ban/chi-tiet/doc--101902"
      },
      {
        "title": "Pháp lệnh 26/2005/PL-UBTVQH11",
        "url": "https://vbpl.vn/van-ban/chi-tiet/doc--vbpqta_6879"
      },
      {
        "title": "Chỉ thị số 21/2013/CT-UBND Về việc triển khai thực hiện Pháp lệnh số 04/2012/UBTVQH13 ngày 16/7/2012 của Uỷ ban thường vụ Quốc hội về việc sửa đổi, bổ sung một số điều của Pháp lệnh ưu đãi người có công  với cách mạng trên địa bàn tỉnh Nghệ An",
        "url": "https://vbpl.vn/van-ban/chi-tiet/doc--50087"
      },
      {
        "title": "Pháp lệnh số 02/2008/PL-UBTVQH12 Công nghiệp quốc phòng",
        "url": "https://vbpl.vn/van-ban/chi-tiet/doc--25983"
      },
      {
        "title": "Pháp lệnh số 31/2000/PL-UBTVQH10 Thư viện",
        "url": "https://vbpl.vn/van-ban/chi-tiet/doc--5746"
      }
    ]
  }
}