{
  "id": "962c6ab0-6966-11f1-950a-f370f719a087",
  "doc_number": "16/2026/NQ-CP",
  "title": "Nghị quyết số 16/2026/NQ-CP Quy định về cơ chế, chính sách tháo gỡ khó khăn, vướng mắc đối với dự án đầu tư theo hình thức Xây dựng - Chuyển giao",
  "doc_type": "Nghị quyết",
  "agency": "Chính phủ",
  "signer": "Nguyễn Hoà Bình",
  "signer_title": "Phó Thủ tướng Chính phủ",
  "issue_date": "2026-04-07",
  "effective_date": "2026-04-07",
  "expire_date": "2027-12-31",
  "status": "Còn hiệu lực",
  "industry": "Tài chính",
  "field": "Đầu tư theo phương thức đối tác công tư",
  "relations": {
    "Căn cứ ban hành": [
      {
        "title": "Luật đầu tư theo phương thức đối tác công tư số 64/2020/QH14",
        "url": "https://vbpl.vn/van-ban/chi-tiet/doc--142882"
      },
      {
        "title": "Luật Tổ chức chính quyền địa phương số 72/2025/QH15",
        "url": "https://vbpl.vn/van-ban/chi-tiet/doc--178340"
      },
      {
        "title": "Nghị quyết số 254/2025/QH15 Quy định một số cơ chế, chính sách tháo gỡ khó khăn, vướng mắc trong tổ chức thi hành Luật Đất đai",
        "url": "https://vbpl.vn/van-ban/chi-tiet/doc--186273"
      },
      {
        "title": "Luật Tổ chức chính phủ số 63/2025/QH15",
        "url": "https://vbpl.vn/van-ban/chi-tiet/doc--175258"
      },
      {
        "title": "Nghị định số 39/2022/NĐ-CP Ban hành Quy chế làm việc của Chính phủ",
        "url": "https://vbpl.vn/van-ban/chi-tiet/doc--179334"
      }
    ]
  }
}