{
  "id": "9402dd90-79c5-11f1-b498-9564c12b186d",
  "doc_number": "272/2026/NĐ-CP",
  "title": "Nghị định số 272/2026/NĐ-CP Quy định chi tiết một số điều và biện pháp để tổ chức, hướng dẫn thi hành Nghị quyết số 253/2025/QH15 ngày 11 tháng 12 năm 2025 của Quốc hội về các cơ chế, chính sách phát triển năng lượng quốc gia giai đoạn 2026 - 2030",
  "doc_type": "Nghị định",
  "agency": "Chính phủ",
  "signer": "Phạm Gia Túc",
  "signer_title": "Phó Thủ tướng Chính phủ",
  "issue_date": "2026-07-04",
  "effective_date": "2026-07-04",
  "expire_date": "2030-12-31",
  "status": "Còn hiệu lực",
  "industry": "Công Thương",
  "field": "Điện lực",
  "relations": {
    "Căn cứ ban hành": [
      {
        "title": "Luật Đấu thầu số 22/2023/QH15",
        "url": "https://vbpl.vn/van-ban/chi-tiet/doc--166581"
      },
      {
        "title": "Luật Điện lực số 61/2024/QH15",
        "url": "https://vbpl.vn/van-ban/chi-tiet/doc--173332"
      },
      {
        "title": "Luật Tổ chức chính phủ số 63/2025/QH15",
        "url": "https://vbpl.vn/van-ban/chi-tiet/doc--175258"
      },
      {
        "title": "Luật Đầu tư số 143/2025/QH15",
        "url": "https://vbpl.vn/van-ban/chi-tiet/doc--187601"
      },
      {
        "title": "Luật Tài nguyên, môi trường biển và hải đảo số 82/2015/QH13",
        "url": "https://vbpl.vn/van-ban/chi-tiet/doc--70804"
      }
    ],
    "Văn bản được hướng dẫn áp dụng": [
      {
        "title": "Nghị quyết số 253/2025/QH15 Về các cơ chế, chính sách phát triển năng lượng quốc gia giai đoạn 2026 - 2030",
        "url": "https://vbpl.vn/van-ban/chi-tiet/doc--186009"
      }
    ]
  }
}