{
  "id": "182363",
  "doc_number": "99/2025/TT-BQP",
  "title": "Thông tư số 99/2025/TT-BQP Quy định về quản lý, sử dụng đất quốc phòng kết hợp với hoạt động lao động sản xuất, xây dựng kinh tế",
  "doc_type": "Thông tư",
  "agency": "Bộ Quốc phòng",
  "signer": "Thượng tướng Vũ Hải Sản",
  "signer_title": "Thứ trưởng",
  "issue_date": "2025-09-03",
  "effective_date": "2025-09-03",
  "expire_date": "--",
  "status": "Còn hiệu lực",
  "industry": "Quốc phòng",
  "field": "Chưa phân loại",
  "relations": {
    "Căn cứ ban hành": [
      {
        "title": "Nghị định số 01/2022/NĐ-CP sửa đổi, bổ sung một số điều của Nghị định số 65/2018/NĐ-CP ngày 12 tháng 5 năm 2018 của Chính phủ quy định chi tiết thi hành một số điều của Luật Đường sắt",
        "url": "https://vbpl.vn/van-ban/chi-tiet/doc--153200"
      },
      {
        "title": "Luật Đất đai số 31/2024/QH15",
        "url": "https://vbpl.vn/van-ban/chi-tiet/doc--177815"
      },
      {
        "title": "Nghị định số 03/2025/NĐ-CP Quy định việc sắp xếp lại, xử lý tài sản công là nhà, đất",
        "url": "https://vbpl.vn/van-ban/chi-tiet/doc--175204"
      },
      {
        "title": "Nghị định số 102/2024/NĐ-CP Quy định chi tiết thi hành một số điều của Luật Đất đai",
        "url": "https://vbpl.vn/van-ban/chi-tiet/doc--169363"
      },
      {
        "title": "Luật Sửa đổi, bổ sung một số điều của Luật Đất đai số 31/2024/QH15, Luật Nhà ở số 27/2023/QH15, Luật Kinh doanh bất động sản số 29/2023/QH15 và Luật Các tổ chức tín dụng số 32/2024/QH15 số 43/2024/QH15",
        "url": "https://vbpl.vn/van-ban/chi-tiet/doc--170509"
      }
    ],
    "Văn bản được dẫn chiếu": [
      {
        "title": "Nghị định số 26/2021/NĐ-CP Quy định chi tiết một số điều của Nghị quyết số 132/2020/QH14 ngày 17 tháng 11 năm 2020 của Quốc hội thí điểm một số chính sách để tháo gỡ vướng mắc, tồn đọng trong quản lý, sử dụng đất quốc phòng, an ninh kết hợp với hoạt động lao động sản xuất, xây dựng kinh tế",
        "url": "https://vbpl.vn/van-ban/chi-tiet/doc--147168"
      },
      {
        "title": "Thông tư số 58/2021/TT-BQP Hướng dẫn thực hiện quy định về thí điểm một số chính sách để tháo gỡ vướng mắc, tồn đọng trong quản lý, sử dụng đất quốc phòng kết hợp với hoạt động lao động sản xuất, xây dựng kinh tế",
        "url": "https://vbpl.vn/van-ban/chi-tiet/doc--148130"
      },
      {
        "title": "Nghị quyết số 132/2020/QH14 Thí điểm một số chính sách để tháo gỡ vướng mắc, tồn đọng trong quản lý, sử dụng đất quốc phòng, an ninh kết hợp \nvới hoạt động sản xuất, xây dựng kinh tế",
        "url": "https://vbpl.vn/van-ban/chi-tiet/doc--147167"
      },
      {
        "title": "Nghị định số 102/2024/NĐ-CP Quy định chi tiết thi hành một số điều của Luật Đất đai",
        "url": "https://vbpl.vn/van-ban/chi-tiet/doc--169363"
      }
    ],
    "Văn bản được thay thế": [
      {
        "title": "Thông tư số 58/2021/TT-BQP Hướng dẫn thực hiện quy định về thí điểm một số chính sách để tháo gỡ vướng mắc, tồn đọng trong quản lý, sử dụng đất quốc phòng kết hợp với hoạt động lao động sản xuất, xây dựng kinh tế",
        "url": "https://vbpl.vn/van-ban/chi-tiet/doc--148130"
      }
    ]
  }
}